screenbolt/__init__.py
screenbolt/compile_resources.py
screenbolt/config.py
screenbolt/image_provider.py
screenbolt/main.py
screenbolt/model.py
screenbolt/qml/components/AnchorButton.qml
screenbolt/qml/components/CustomButton.qml
screenbolt/qml/components/GradientPreview.qml
screenbolt/qml/components/ModeButton.qml
screenbolt/qml/components/RecordButton.qml
screenbolt/qml/countdown/Countdown.qml
screenbolt/qml/entry/ControlPanel.qml
screenbolt/qml/entry/CustomSelector.qml
screenbolt/qml/entry/ScreenBolt.qml
screenbolt/qml/entry/main.qml
screenbolt/qml/studio/ClipTrack.qml
screenbolt/qml/studio/ControlButtons.qml
screenbolt/qml/studio/ExportDialog.qml
screenbolt/qml/studio/MainContent.qml
screenbolt/qml/studio/Studio.qml
screenbolt/qml/studio/TimeSlider.qml
screenbolt/qml/studio/Timeline.qml
screenbolt/qml/studio/TopBar.qml
screenbolt/qml/studio/VideoEdit.qml
screenbolt/qml/studio/VideoPreview.qml
screenbolt/qml/studio/sidebar/SideBar.qml
screenbolt/qml/studio/sidebar/background_settings/BackgroundSettings.qml
screenbolt/qml/studio/sidebar/background_settings/ColorPage.qml
screenbolt/qml/studio/sidebar/background_settings/GradientPage.qml
screenbolt/qml/studio/sidebar/background_settings/ImagePage.qml
screenbolt/qml/studio/sidebar/background_settings/WallpaperPage.qml
screenbolt/qml/studio/sidebar/shape_settings/ShapeSettings.qml
screenbolt/rc_icons.py
screenbolt/rc_images.py
screenbolt/rc_main.py
screenbolt/resources/icons/add.svg
screenbolt/resources/icons/ar_16_9.svg
screenbolt/resources/icons/ar_1_1.svg
screenbolt/resources/icons/ar_3_4.svg
screenbolt/resources/icons/ar_4_3.svg
screenbolt/resources/icons/ar_9_16.svg
screenbolt/resources/icons/ar_auto.svg
screenbolt/resources/icons/back.svg
screenbolt/resources/icons/background.svg
screenbolt/resources/icons/border.svg
screenbolt/resources/icons/clip.svg
screenbolt/resources/icons/clock.svg
screenbolt/resources/icons/close.svg
screenbolt/resources/icons/cursor.svg
screenbolt/resources/icons/custom.svg
screenbolt-1.1.0.dist-info/LICENSE
screenbolt-1.1.0.dist-info/METADATA
screenbolt-1.1.0.dist-info/WHEEL
screenbolt-1.1.0.dist-info/entry_points.txt
screenbolt-1.1.0.dist-info/RECORD
