Metadata-Version: 2.1
Name: screenbolt
Version: 1.1.0
Summary: ScreenBolt - A PySide6-based GUI application for screen recording and editing.
License: MIT
Author: Your Name
Author-email: your.email@example.com
Requires-Python: >=3.8,<4.0
Classifier: License :: OSI Approved :: MIT License
Classifier: Programming Language :: Python :: 3
Classifier: Programming Language :: Python :: 3.8
Classifier: Programming Language :: Python :: 3.9
Classifier: Programming Language :: Python :: 3.10
Classifier: Programming Language :: Python :: 3.11
Classifier: Programming Language :: Python :: 3.12
Requires-Dist: Pillow (>=7.0,<=10.4.0)
Requires-Dist: PySide6 (>=6.2.4,<7.0)
Requires-Dist: mss (>=9.0.1,<10)
Requires-Dist: opencv-python (>=4.6.0,<=4.10.0.84)
Requires-Dist: pyautogui (>=0.9.54,<1.0)
